test_database/__init__.py
test_database/connector.py
test_suite/__init__.py
test_suite/mysql_tests.py
lins_test_database_mocker-1.0.0.dist-info/LICENSE
lins_test_database_mocker-1.0.0.dist-info/METADATA
lins_test_database_mocker-1.0.0.dist-info/WHEEL
lins_test_database_mocker-1.0.0.dist-info/top_level.txt
lins_test_database_mocker-1.0.0.dist-info/RECORD
