Metadata-Version: 2.1
Name: lins-test-database-mocker
Version: 1.0.0
Summary: Lib para criação e população de databases para testes.
Home-page: https://bitbucket.org/grupolinsferrao/pypck-lins-test-database-mocker
Author: Diego Magalhães
Author-email: diego.magalhaes@dbccompany.com.br
License: UNKNOWN
Platform: UNKNOWN
Classifier: Programming Language :: Python :: 3
Classifier: License :: OSI Approved :: MIT License
Classifier: Operating System :: OS Independent
Requires-Python: >=3.6
Requires-Dist: pymysql
